README.md
setup.cfg
setup.py
dataswim/__init__.py
dataswim/base.py
dataswim/errors.py
dataswim/messages.py
dataswim/report.py
dataswim.egg-info/PKG-INFO
dataswim.egg-info/SOURCES.txt
dataswim.egg-info/dependency_links.txt
dataswim.egg-info/not-zip-safe
dataswim.egg-info/requires.txt
dataswim.egg-info/top_level.txt
dataswim/charts/__init__.py
dataswim/charts/altair.py
dataswim/charts/bokeh.py
dataswim/charts/chartjs.py
dataswim/charts/colors.py
dataswim/charts/seaborn.py
dataswim/data/__init__.py
dataswim/data/clean.py
dataswim/data/count.py
dataswim/data/export.py
dataswim/data/search.py
dataswim/data/select.py
dataswim/data/stats.py
dataswim/data/text.py
dataswim/data/views.py
dataswim/data/transform/__init__.py
dataswim/data/transform/calculations.py
dataswim/data/transform/columns.py
dataswim/data/transform/dataframe.py
dataswim/data/transform/resample.py
dataswim/data/transform/values.py
dataswim/db/__init__.py
dataswim/db/base.py
dataswim/db/infos.py
dataswim/db/insert.py
dataswim/db/query.py
dataswim/db/relations.py
dataswim/db/select.py
dataswim/db/influxdb/__init__.py
dataswim/db/sqlite/__init__.py
dataswim/maps/__init__.py
dataswim/tests/__init__.py
dataswim/tests/__main__.py
dataswim/tests/base.py
dataswim/tests/data/__init__.py
dataswim/tests/data/test_clean.py
dataswim/tests/data/test_count.py
dataswim/tests/data/test_init.py
dataswim/tests/data/test_search.py
dataswim/tests/data/test_select.py
dataswim/tests/data/test_stats.py
dataswim/tests/data/test_text.py
dataswim/tests/data/test_transform.py