Metadata-Version: 1.1
Name: dataswim
Version: 0.5.1
Summary: Diving equipment for data lake
Home-page: https://github.com/synw/dataswim
Author: synw
Author-email: synwe@yahoo.com
License: UNKNOWN
Download-URL: https://github.com/synw/dataswim/releases/tag/0.5.1
Keywords: data_visualization,data_exploration,charts
Platform: UNKNOWN
Classifier: Development Status :: 3 - Alpha
Classifier: Intended Audience :: Developers
Classifier: License :: OSI Approved :: MIT License
Classifier: Programming Language :: Python :: 3.6
